ctrl-v.py
ctrlv_entry.py
ctrlv_client/__init__.py
ctrlv_client/config.py
ctrlv_client/populate.json
ctrlv_client/app/__init__.py
ctrlv_client/app/helpers.py
ctrlv_client/app/main/__init__.py
ctrlv_client/app/main/forms.py
ctrlv_client/app/main/views.py
ctrlv_client/app/models/__init__.py
ctrlv_client/app/models/snippet.py
ctrlv_client/app/models/tags.py
ctrlv_client/app/models/user.py
ctrlv_client/app/static/css/app.css
ctrlv_client/app/static/css/bootstrap.min.css
ctrlv_client/app/static/css/fontawesome/css/fontawesome.min.css
ctrlv_client/app/static/css/fontawesome/css/solid.min.css
ctrlv_client/app/static/css/fontawesome/webfonts/fa-brands-400.eot
ctrlv_client/app/static/css/fontawesome/webfonts/fa-brands-400.svg
ctrlv_client/app/static/css/fontawesome/webfonts/fa-brands-400.ttf
ctrlv_client/app/static/css/fontawesome/webfonts/fa-brands-400.woff
ctrlv_client/app/static/css/fontawesome/webfonts/fa-brands-400.woff2
ctrlv_client/app/static/css/fontawesome/webfonts/fa-regular-400.eot
ctrlv_client/app/static/css/fontawesome/webfonts/fa-regular-400.svg
ctrlv_client/app/static/css/fontawesome/webfonts/fa-regular-400.ttf
ctrlv_client/app/static/css/fontawesome/webfonts/fa-regular-400.woff
ctrlv_client/app/static/css/fontawesome/webfonts/fa-regular-400.woff2
ctrlv_client/app/static/css/fontawesome/webfonts/fa-solid-900.eot
ctrlv_client/app/static/css/fontawesome/webfonts/fa-solid-900.svg
ctrlv_client/app/static/css/fontawesome/webfonts/fa-solid-900.ttf
ctrlv_client/app/static/css/fontawesome/webfonts/fa-solid-900.woff
ctrlv_client/app/static/css/fontawesome/webfonts/fa-solid-900.woff2
ctrlv_client/app/static/js/bootstrap-select.min.js
ctrlv_client/app/static/js/bootstrap.min.js
ctrlv_client/app/static/js/jquery-3.3.1.slim.min.js
ctrlv_client/app/static/js/masonry.pkgd.js
ctrlv_client/app/static/js/popper.min.js
ctrlv_client/app/static/js/tags.js
ctrlv_client/app/tag/__init__.py
ctrlv_client/app/tag/forms.py
ctrlv_client/app/tag/views.py
ctrl_v-0.2.0.dist-info/LICENSE
ctrl_v-0.2.0.dist-info/METADATA
ctrl_v-0.2.0.dist-info/WHEEL
ctrl_v-0.2.0.dist-info/entry_points.txt
ctrl_v-0.2.0.dist-info/top_level.txt
ctrl_v-0.2.0.dist-info/RECORD
